mcp_nano_banana/__init__.py
mcp_nano_banana/main.py
mcp_nano_banana/test_gemini.py
mcp_nano_banana-0.3.3.dist-info/METADATA
mcp_nano_banana-0.3.3.dist-info/WHEEL
mcp_nano_banana-0.3.3.dist-info/entry_points.txt
mcp_nano_banana-0.3.3.dist-info/top_level.txt
mcp_nano_banana-0.3.3.dist-info/RECORD
