Metadata-Version: 2.4
Name: mcp-nano-banana
Version: 0.3.3
Summary: Um servidor MCP que gera imagens usando a Google Gemini API.
Project-URL: Homepage, https://github.com/GuilhermeAumo/mcp-nano-banana
Project-URL: Repository, https://github.com/GuilhermeAumo/mcp-nano-banana
Requires-Python: ==3.10
Requires-Dist: mcp[cli]==1.13
Requires-Dist: google-generativeai==0.5.4
Requires-Dist: python-dotenv==1.0.1
Requires-Dist: pillow==11.3.0
